MANIFEST.in
Makefile
README
build.bu
setup.py
tox.ini
Flask_Creole.egg-info/PKG-INFO
Flask_Creole.egg-info/SOURCES.txt
Flask_Creole.egg-info/dependency_links.txt
Flask_Creole.egg-info/namespace_packages.txt
Flask_Creole.egg-info/not-zip-safe
Flask_Creole.egg-info/requires.txt
Flask_Creole.egg-info/top_level.txt
docs/conf.py
docs/index.rst
docs/_themes/LICENSE
docs/_themes/README
docs/_themes/flask_theme_support.py
docs/_themes/flask_theme_support.pyc
docs/_themes/flask_small/layout.html
docs/_themes/flask_small/theme.conf
docs/_themes/flask_small/static/flasky.css_t
flaskext/__init__.py
flaskext/creole.py
tests/test_creole.py