Metadata-Version: 1.0
Name: Flask-Creole
Version: 0.4.4
Summary: Creole parser filters for Flask
Home-page: http://bitbucket.org/aafshar/flask-creole-main
Author: Ali Afshar
Author-email: aafshar@gmail.com
License: MIT
Platform: any
Classifier: Development Status :: 4 - Beta
Classifier: Environment :: Web Environment
Classifier: Intended Audience :: Developers
Classifier: License :: OSI Approved :: MIT License
Classifier: Operating System :: OS Independent
Classifier: Programming Language :: Python
Classifier: Topic :: Internet :: WWW/HTTP :: Dynamic Content
Classifier: Topic :: Software Development :: Libraries :: Python Modules
